[
  {
    "name": "Radio Futura",
    "url": "https://stream-165.zeno.fm/iwmolyow6tivv",
    "logoUrl": "https://radiofuturanicaragua.com/images/logo-futura.png"
  },
  {
    "name": "Clásica",
    "url": "https://stream-164.zeno.fm/ilzuypllpo7vv",
    "logoUrl": "https://zeno.fm/_ipx/_/https://images.zeno.fm/HFZBfprumQLjAFSjQ5LqLI8ugsHQ18dEj02bF_1JCNM/rs:fill:256:256/g:ce:0:0/aHR0cHM6Ly9wcm94eS56ZW5vLmZtL2NvbnRlbnQvc3RhdGlvbnMvODUyODU0ZDktMDE4My00MDQ5LWE2YmYtMjc1MjU5YjhjNjgxL2ltYWdlLz91PTE3MjU0NTkzODAwMDA.webp"
  },
  {
    "name": "Joya FM",
    "url": "https://stream-153.zeno.fm/2wbv6enf1mruv",
    "logoUrl": "https://images.keepone.net/9759-2023-09-26.jpg"
  } 
]
